[{"objectId":"u873HimxTg","iso2":null,"Country_Code":"NA","Subdivision_Code":"OW","Subdivion_Type":"Region","Subdivision_Name":"Ohangwena"},{"objectId":"YDqQ3iH3m0","iso2":null,"Country_Code":"NA","Subdivision_Code":"KH","Subdivion_Type":"Region","Subdivision_Name":"Khomas"},{"objectId":"eTS8N75qX8","iso2":null,"Country_Code":"NA","Subdivision_Code":"OD","Subdivion_Type":"Region","Subdivision_Name":"Otjozondjupa"},{"objectId":"9osQgkKW5R","iso2":null,"Country_Code":"NA","Subdivision_Code":"ER","Subdivion_Type":"Region","Subdivision_Name":"Erongo"},{"objectId":"ZE3knHWIfN","iso2":null,"Country_Code":"NA","Subdivision_Code":"KE","Subdivion_Type":"Region","Subdivision_Name":"Kavango East"},{"objectId":"ynbhCRv1hN","iso2":null,"Country_Code":"NA","Subdivision_Code":"KA","Subdivion_Type":"Region","Subdivision_Name":"Karas"},{"objectId":"TSiF5Ek0Yy","iso2":null,"Country_Code":"NA","Subdivision_Code":"OH","Subdivion_Type":"Region","Subdivision_Name":"Omaheke"},{"objectId":"eYepV8n1Mv","iso2":null,"Country_Code":"NA","Subdivision_Code":"OS","Subdivion_Type":"Region","Subdivision_Name":"Omusati"},{"objectId":"cSIdLJLFJc","iso2":null,"Country_Code":"NA","Subdivision_Code":"HA","Subdivion_Type":"Region","Subdivision_Name":"Hardap"},{"objectId":"G7CVmGPD25","iso2":null,"Country_Code":"NA","Subdivision_Code":"CA","Subdivion_Type":"Region","Subdivision_Name":"Zambezi"},{"objectId":"ZMtl6d33XB","iso2":null,"Country_Code":"NA","Subdivision_Code":"ON","Subdivion_Type":"Region","Subdivision_Name":"Oshana"},{"objectId":"fgSCk4cHAZ","iso2":null,"Country_Code":"NA","Subdivision_Code":"KU","Subdivion_Type":"Region","Subdivision_Name":"Kunene"},{"objectId":"Gibzwt2ENR","iso2":null,"Country_Code":"NA","Subdivision_Code":"KW","Subdivion_Type":null,"Subdivision_Name":"Kavango West"},{"objectId":"QSLGMN5bWB","iso2":null,"Country_Code":"NA","Subdivision_Code":"OT","Subdivion_Type":"Region","Subdivision_Name":"Oshikoto"}]