[{"country":{"objectId":"9CVfAKT2WO","__type":"Pointer","className":"Continentscountriescities_Country"},"objectId":"4czRLQGX9s","cityId":1040989,"name":"Manhiça"},{"country":{"objectId":"9CVfAKT2WO","__type":"Pointer","className":"Continentscountriescities_Country"},"objectId":"1wIBMINNpZ","cityId":1024701,"name":"Macia"},{"country":{"objectId":"9CVfAKT2WO","__type":"Pointer","className":"Continentscountriescities_Country"},"objectId":"RMYhJ08gP2","cityId":1045114,"name":"Inhambane"},{"country":{"objectId":"9CVfAKT2WO","__type":"Pointer","className":"Continentscountriescities_Country"},"objectId":"PuWAKIfDUa","cityId":1024552,"name":"Xai-Xai"},{"country":{"objectId":"9CVfAKT2WO","__type":"Pointer","className":"Continentscountriescities_Country"},"objectId":"Kh1RhMACfN","cityId":1024696,"name":"Dondo"},{"country":{"objectId":"9CVfAKT2WO","__type":"Pointer","className":"Continentscountriescities_Country"},"objectId":"5NZGW6gN5L","cityId":1026014,"name":"Tete"},{"country":{"objectId":"9CVfAKT2WO","__type":"Pointer","className":"Continentscountriescities_Country"},"objectId":"Gspk4ZRhiS","cityId":1048364,"name":"Chokwé"},{"country":{"objectId":"9CVfAKT2WO","__type":"Pointer","className":"Continentscountriescities_Country"},"objectId":"51HAMXGXLa","cityId":1052373,"name":"Beira"},{"country":{"objectId":"9CVfAKT2WO","__type":"Pointer","className":"Continentscountriescities_Country"},"objectId":"mYBKfTT6vI","cityId":1040938,"name":"Manjacaze"},{"country":{"objectId":"9CVfAKT2WO","__type":"Pointer","className":"Continentscountriescities_Country"},"objectId":"16drzaPmhM","cityId":1028918,"name":"Pemba"},{"country":{"objectId":"9CVfAKT2WO","__type":"Pointer","className":"Continentscountriescities_Country"},"objectId":"qOZNB2zONk","cityId":1037390,"name":"Ilha de Moçambique"},{"country":{"objectId":"9CVfAKT2WO","__type":"Pointer","className":"Continentscountriescities_Country"},"objectId":"7mQVhFV6nt","cityId":1037125,"name":"Montepuez"},{"country":{"objectId":"9CVfAKT2WO","__type":"Pointer","className":"Continentscountriescities_Country"},"objectId":"CqqMBZIn8e","cityId":1040652,"name":"Maputo"},{"country":{"objectId":"9CVfAKT2WO","__type":"Pointer","className":"Continentscountriescities_Country"},"objectId":"5sHPeKB95o","cityId":1028079,"name":"Ressano Garcia"},{"country":{"objectId":"9CVfAKT2WO","__type":"Pointer","className":"Continentscountriescities_Country"},"objectId":"7dic2dKEGc","cityId":1037370,"name":"Mocímboa"},{"country":{"objectId":"9CVfAKT2WO","__type":"Pointer","className":"Continentscountriescities_Country"},"objectId":"l6Qo1JoqDu","cityId":1088155,"name":"Mutuáli"},{"country":{"objectId":"9CVfAKT2WO","__type":"Pointer","className":"Continentscountriescities_Country"},"objectId":"aAmQqtl1gx","cityId":1052944,"name":"António Enes"},{"country":{"objectId":"9CVfAKT2WO","__type":"Pointer","className":"Continentscountriescities_Country"},"objectId":"ADkYJhxw0S","cityId":1028434,"name":"Quelimane"},{"country":{"objectId":"9CVfAKT2WO","__type":"Pointer","className":"Continentscountriescities_Country"},"objectId":"wC6vvol6Ie","cityId":1043893,"name":"Lichinga"},{"country":{"objectId":"9CVfAKT2WO","__type":"Pointer","className":"Continentscountriescities_Country"},"objectId":"HvfNjtZbIA","cityId":1035025,"name":"Nacala"},{"country":{"objectId":"9CVfAKT2WO","__type":"Pointer","className":"Continentscountriescities_Country"},"objectId":"N2j4xuZlK0","cityId":1049861,"name":"Chibuto"},{"country":{"objectId":"9CVfAKT2WO","__type":"Pointer","className":"Continentscountriescities_Country"},"objectId":"y952EKG3r4","cityId":1039854,"name":"Matola"},{"country":{"objectId":"9CVfAKT2WO","__type":"Pointer","className":"Continentscountriescities_Country"},"objectId":"UEsjuyajUj","cityId":1049261,"name":"Chimoio"},{"country":{"objectId":"9CVfAKT2WO","__type":"Pointer","className":"Continentscountriescities_Country"},"objectId":"63lzFfdwxv","cityId":1033356,"name":"Nampula"},{"country":{"objectId":"9CVfAKT2WO","__type":"Pointer","className":"Continentscountriescities_Country"},"objectId":"PSZWX6DtUw","cityId":1039536,"name":"Maxixe"},{"country":{"objectId":"9CVfAKT2WO","__type":"Pointer","className":"Continentscountriescities_Country"},"objectId":"jJg4Y4ug5F","cityId":1047660,"name":"Cuamba"}]